MANIFEST.in
README.md
setup.cfg
setup.py
user_discord/__init__.py
user_discord/socket.py
user_discord/user_discord.py
user_discord.egg-info/PKG-INFO
user_discord.egg-info/SOURCES.txt
user_discord.egg-info/dependency_links.txt
user_discord.egg-info/requires.txt
user_discord.egg-info/top_level.txt
user_discord/discord/__init__.py
user_discord/discord/__main__.py
user_discord/discord/abc.py
user_discord/discord/activity.py
user_discord/discord/affinity.py
user_discord/discord/application.py
user_discord/discord/asset.py
user_discord/discord/audit_logs.py
user_discord/discord/automod.py
user_discord/discord/backoff.py
user_discord/discord/billing.py
user_discord/discord/calls.py
user_discord/discord/channel.py
user_discord/discord/client.py
user_discord/discord/colour.py
user_discord/discord/commands.py
user_discord/discord/components.py
user_discord/discord/connections.py
user_discord/discord/context_managers.py
user_discord/discord/embeds.py
user_discord/discord/emoji.py
user_discord/discord/entitlements.py
user_discord/discord/enums.py
user_discord/discord/errors.py
user_discord/discord/file.py
user_discord/discord/flags.py
user_discord/discord/gateway.py
user_discord/discord/guild.py
user_discord/discord/guild_premium.py
user_discord/discord/handlers.py
user_discord/discord/http.py
user_discord/discord/integrations.py
user_discord/discord/interactions.py
user_discord/discord/invite.py
user_discord/discord/library.py
user_discord/discord/member.py
user_discord/discord/mentions.py
user_discord/discord/message.py
user_discord/discord/metadata.py
user_discord/discord/mixins.py
user_discord/discord/modal.py
user_discord/discord/object.py
user_discord/discord/oggparse.py
user_discord/discord/opus.py
user_discord/discord/partial_emoji.py
user_discord/discord/payments.py
user_discord/discord/permissions.py
user_discord/discord/player.py
user_discord/discord/profile.py
user_discord/discord/promotions.py
user_discord/discord/raw_models.py
user_discord/discord/reaction.py
user_discord/discord/relationship.py
user_discord/discord/role.py
user_discord/discord/scheduled_event.py
user_discord/discord/settings.py
user_discord/discord/stage_instance.py
